{
  "code": 0,
  "message": "success",
  "data": [
    {
      "salesperson_id": "3331482000000796037",
      "salesperson_name": "AHAMED ASIF",
      "salesperson_email": "",
      "salesperson_mobile": "",
      "crm_reference_id": "",
      "is_active": true
    },
    {
      "salesperson_id": "3331482000000796039",
      "salesperson_name": "MANSOOR",
      "salesperson_email": "",
      "salesperson_mobile": "",
      "crm_reference_id": "",
      "is_active": true
    },
    {
      "salesperson_id": "3331482000000796096",
      "salesperson_name": "DILEEP KUMAR",
      "salesperson_email": "",
      "salesperson_mobile": "",
      "crm_reference_id": "",
      "is_active": true
    },
    {
      "salesperson_id": "3331482000000838397",
      "salesperson_name": "KHALIFA",
      "salesperson_email": "khaliifa@nellonfoods.com",
      "salesperson_mobile": "",
      "crm_reference_id": "",
      "is_active": true
    },
    {
      "salesperson_id": "3331482000001449184",
      "salesperson_name": "SHAMEER TAYYIL&HASHIM",
      "salesperson_email": "",
      "salesperson_mobile": "",
      "crm_reference_id": "",
      "is_active": true
    },
    {
      "salesperson_id": "3331482000002075001",
      "salesperson_name": " FAISAL VADAKKATH ",
      "salesperson_email": "",
      "salesperson_mobile": "",
      "crm_reference_id": "",
      "is_active": true
    },
    {
      "salesperson_id": "3331482000002644173",
      "salesperson_name": "HASHIM ARAKAL",
      "salesperson_email": "",
      "salesperson_mobile": "",
      "crm_reference_id": "",
      "is_active": true
    },
    {
      "salesperson_id": "3331482000005798292",
      "salesperson_name": "SARUN ",
      "salesperson_email": "",
      "salesperson_mobile": "",
      "crm_reference_id": "",
      "is_active": true
    },
    {
      "salesperson_id": "3331482000006369121",
      "salesperson_name": "YOONUS",
      "salesperson_email": "",
      "salesperson_mobile": "",
      "crm_reference_id": "",
      "is_active": true
    },
    {
      "salesperson_id": "3331482000006369123",
      "salesperson_name": "SABAH ABUDABI",
      "salesperson_email": "",
      "salesperson_mobile": "",
      "crm_reference_id": "",
      "is_active": true
    },
    {
      "salesperson_id": "3331482000007244983",
      "salesperson_name": "MUSHIN",
      "salesperson_email": "",
      "salesperson_mobile": "",
      "crm_reference_id": "",
      "is_active": true
    },
    {
      "salesperson_id": "3331482000007794735",
      "salesperson_name": "MUHAMED SHAFI",
      "salesperson_email": "",
      "salesperson_mobile": "",
      "crm_reference_id": "",
      "is_active": true
    },
    {
      "salesperson_id": "3331482000015297587",
      "salesperson_name": "ASHRAF ALI",
      "salesperson_email": "",
      "salesperson_mobile": "",
      "crm_reference_id": "",
      "is_active": true
    },
    {
      "salesperson_id": "3331482000028075285",
      "salesperson_name": "NAJEEB",
      "salesperson_email": "",
      "salesperson_mobile": "",
      "crm_reference_id": "",
      "is_active": true
    },
    {
      "salesperson_id": "3331482000030476199",
      "salesperson_name": "SHIHAS",
      "salesperson_email": "",
      "salesperson_mobile": "",
      "crm_reference_id": "",
      "is_active": true
    },
    {
      "salesperson_id": "3331482000036517745",
      "salesperson_name": "UNION COP",
      "salesperson_email": "",
      "salesperson_mobile": "",
      "crm_reference_id": "",
      "is_active": true
    },
    {
      "salesperson_id": "3331482000036517747",
      "salesperson_name": "KSA",
      "salesperson_email": "",
      "salesperson_mobile": "",
      "crm_reference_id": "",
      "is_active": true
    },
    {
      "salesperson_id": "3331482000036785681",
      "salesperson_name": "NELLON",
      "salesperson_email": "",
      "salesperson_mobile": "",
      "crm_reference_id": "",
      "is_active": true
    },
    {
      "salesperson_id": "3331482000036864227",
      "salesperson_name": "ARAB ASIA KWT",
      "salesperson_email": "",
      "salesperson_mobile": "",
      "crm_reference_id": "",
      "is_active": true
    },
    {
      "salesperson_id": "3331482000036864513",
      "salesperson_name": "ABUDABI DISTRIBUTION",
      "salesperson_email": "",
      "salesperson_mobile": "",
      "crm_reference_id": "",
      "is_active": true
    },
    {
      "salesperson_id": "3331482000036864515",
      "salesperson_name": "QATAR",
      "salesperson_email": "",
      "salesperson_mobile": "",
      "crm_reference_id": "",
      "is_active": true
    },
    {
      "salesperson_id": "3331482000048131079",
      "salesperson_name": "MUHAMMED FAVAS",
      "salesperson_email": "",
      "salesperson_mobile": "",
      "crm_reference_id": "",
      "is_active": true
    },
    {
      "salesperson_id": "3331482000063884023",
      "salesperson_name": "RIZWAN",
      "salesperson_email": "",
      "salesperson_mobile": "",
      "crm_reference_id": "",
      "is_active": true
    },
    {
      "salesperson_id": "3331482000082454188",
      "salesperson_name": "HASHIM",
      "salesperson_email": "",
      "salesperson_mobile": "",
      "crm_reference_id": "",
      "is_active": true
    },
    {
      "salesperson_id": "3331482000083905391",
      "salesperson_name": "NASAR",
      "salesperson_email": "",
      "salesperson_mobile": "",
      "crm_reference_id": "",
      "is_active": true
    },
    {
      "salesperson_id": "3331482000100060579",
      "salesperson_name": "OMAN",
      "salesperson_email": "",
      "salesperson_mobile": "",
      "crm_reference_id": "",
      "is_active": true
    },
    {
      "salesperson_id": "3331482000105822316",
      "salesperson_name": "SHIHAB DEIRA",
      "salesperson_email": "",
      "salesperson_mobile": "",
      "crm_reference_id": "",
      "is_active": true
    },
    {
      "salesperson_id": "3331482000111780930",
      "salesperson_name": "SHANOOB DRINK",
      "salesperson_email": "",
      "salesperson_mobile": "",
      "crm_reference_id": "",
      "is_active": true
    },
    {
      "salesperson_id": "3331482000142355455",
      "salesperson_name": "RINSHAD ",
      "salesperson_email": "",
      "salesperson_mobile": "",
      "crm_reference_id": "",
      "is_active": true
    },
    {
      "salesperson_id": "3331482000142775707",
      "salesperson_name": "SHAMIL AUH",
      "salesperson_email": "",
      "salesperson_mobile": "",
      "crm_reference_id": "",
      "is_active": true
    },
    {
      "salesperson_id": "3331482000180728088",
      "salesperson_name": "SHINAD",
      "salesperson_email": "",
      "salesperson_mobile": "",
      "crm_reference_id": "",
      "is_active": true
    }
  ]
}